nvsmifs/__init__.py
nvsmifs-1.1.0.dist-info/LICENSE.txt
nvsmifs-1.1.0.dist-info/METADATA
nvsmifs-1.1.0.dist-info/WHEEL
nvsmifs-1.1.0.dist-info/entry_points.txt
nvsmifs-1.1.0.dist-info/RECORD
