Metadata-Version: 2.1
Name: nvsmifs
Version: 1.1.0
Summary: A (user-)friendly wrapper to nvidia-smi
Home-page: https://github.com/initiateit/nvsmifs
License: MIT
Keywords: nvidia,gpu,nvidia-smi,cli,hardware,monitoring
Author: Panos Mavrogiorgos
Author-email: pmav99@gmail.com
Requires-Python: >=3.6,<4.0
Classifier: Environment :: Console
Classifier: License :: OSI Approved :: MIT License
Classifier: Operating System :: POSIX :: Linux
Classifier: Programming Language :: Python :: 3
Classifier: Programming Language :: Python :: 3.6
Classifier: Programming Language :: Python :: 3.7
Classifier: Programming Language :: Python :: 3.8
Classifier: Programming Language :: Python :: 3.9
Classifier: Programming Language :: Python :: 3.10
Classifier: Programming Language :: Python :: 3.11
Classifier: Programming Language :: Python :: 3.12
Classifier: Programming Language :: Python :: 3.13
Classifier: Topic :: System :: Hardware :: Hardware Drivers
Project-URL: Documentation, https://github.com/initiateit/nvsmifs
Project-URL: Repository, https://github.com/initiateit/nvsmifs
